fcs_simulation
