Metadata-Version: 1.0
Name: fcs-simulation
Version: 0.1.1f
Summary: Simulate FCS and generate photon arrival times
Home-page: http://github.com/computemachines/fcs_simulation
Author: Tyler Parker
Author-email: tparker@umass.edu
License: MIT
Platform: UNKNOWN
